src/DockerActive.py
src/K8sActive.py
src/ProjcetActive.py
src/__init__.py
src/__main__.py
src/main.py
jjckdockertool-2.dist-info/METADATA
jjckdockertool-2.dist-info/WHEEL
jjckdockertool-2.dist-info/top_level.txt
jjckdockertool-2.dist-info/RECORD
